{
  "product": [
    {
      "name": "payal",
      "karat": "22",
      "weight": "22",
      "price": "2222",
      "image": "https://png.pngtree.com/png-vector/20210618/ourmid/pngtree-gold-chain-collar-metal-accessories-png-image_3443360.jpg",
      "id": 44
    },
    {
      "name": "chai2",
      "karat": "12",
      "weight": "11",
      "price": "13313",
      "image": "https://png.pngtree.com/png-vector/20210618/ourmid/pngtree-gold-chain-collar-metal-accessories-png-image_3443360.jpg",
      "id": 45
    },
    {
      "name": "test67",
      "karat": "33",
      "weight": "33",
      "price": "44",
      "image": "./ring.jpg",
      "id": 66
    },
    {
      "name": "ttt",
      "karat": "33",
      "weight": "12",
      "price": "12",
      "image": "./ring.jpg",
      "id": 67
    },
    {
      "name": "t",
      "karat": "121",
      "weight": "12",
      "price": "12",
      "image": "./ring.jpg",
      "id": 68
    },
    {
      "name": "ttt",
      "karat": "22",
      "weight": "22",
      "price": "22",
      "image": "./ring.jpg",
      "id": 69
    },
    {
      "name": "ee",
      "karat": "22",
      "weight": "22",
      "price": "22",
      "image": "./ring.jpg",
      "id": 71
    },
    {
      "name": "t",
      "karat": "33",
      "weight": "33",
      "price": "33",
      "image": "./ring.jpg",
      "id": 72
    },
    {
      "name": "test",
      "karat": "12",
      "weight": "12",
      "price": "12",
      "image": "./ring.jpg",
      "id": 73
    },
    {
      "name": "testh",
      "karat": "1212",
      "weight": "12",
      "price": "12",
      "image": "./ring.jpg",
      "id": 74
    },
    {
      "name": "tt",
      "karat": "44",
      "weight": "22",
      "price": "22",
      "image": "./hearing.png",
      "id": 75
    },
    {
      "name": "y",
      "karat": "33",
      "weight": "33",
      "price": "33",
      "image": "./hearing.png",
      "id": 76
    },
    {
      "name": "t",
      "karat": "22",
      "weight": "22",
      "price": "22",
      "image": "./hearing.png",
      "id": 77
    },
    {
      "name": "t",
      "karat": "23",
      "weight": "12",
      "price": "12",
      "image": "./hearing.png",
      "id": 78
    },
    {
      "name": "rr",
      "karat": "22",
      "weight": "22",
      "price": "22",
      "image": "./ring copy.jpg",
      "id": 81
    },
    {
      "name": "rings",
      "karat": "12",
      "weight": "12",
      "price": "12",
      "image": "./hearing.png",
      "id": 82
    },
    {
      "name": "tt",
      "karat": "22",
      "weight": "22",
      "price": "22",
      "image": "./ring copy.jpg",
      "id": 83
    },
    {
      "name": "f",
      "karat": "22",
      "weight": "222",
      "price": "22",
      "image": false,
      "id": 84
    },
    {
      "name": "test",
      "karat": "22",
      "weight": "22",
      "price": "22",
      "image": "./ring copy.jpg",
      "id": 85
    },
    {
      "name": "d",
      "karat": "24",
      "weight": "22",
      "price": "22",
      "image": false,
      "id": 86
    }
  ]
}